Metadata-Version: 1.0
Name: udac-distributions
Version: 0.1
Summary: Gaussian and Binomial distributions
Home-page: UNKNOWN
Author: Chidimma Nweke
Author-email: realchidinweke@gmail.com
License: UNKNOWN
Platform: UNKNOWN
